toxicityclassifier/__init__.py
toxicityclassifier/models/EnglishModel.bf
toxicityclassifier/models/EnglishVectorizer.bf
toxicityclassifier/models/RussianModel.bf
toxicityclassifier/models/RussianVectorizer.bf
toxicityclassifier/toxicityclassifier.py
toxicityclassifier-1.0.1.dist-info/LICENSE.md
toxicityclassifier-1.0.1.dist-info/METADATA
toxicityclassifier-1.0.1.dist-info/WHEEL
toxicityclassifier-1.0.1.dist-info/RECORD
