Metadata-Version: 2.1
Name: toxicityclassifier
Version: 1.0.1
Summary: Module for determining the level of toxicity of the text
Home-page: https://github.com/D1ffic00lt/toxicity-classification-module
License: MIT
Author: D1ffic00lt
Author-email: dm.filinov@gmail.com
Requires-Python: >=3.8,<4.0
Classifier: License :: OSI Approved :: MIT License
Classifier: Programming Language :: Python :: 3
Classifier: Programming Language :: Python :: 3.8
Classifier: Programming Language :: Python :: 3.9
Classifier: Programming Language :: Python :: 3.10
Classifier: Programming Language :: Python :: 3.11
Classifier: Programming Language :: Python :: 3.12
Project-URL: Documentation, https://github.com/D1ffic00lt/toxicity-classification-module/blob/main/README.md
Project-URL: Repository, https://github.com/D1ffic00lt/toxicity-classification-module
